Metadata-Version: 2.1
Name: tap-typeform
Version: 2.4.0
Summary: Singer.io tap for extracting data from the TypeForm Responses API
Home-page: http://singer.io
Author: bytcode.io
Classifier: Programming Language :: Python :: 3 :: Only
Provides-Extra: dev
License-File: LICENSE
